{
  "people": {
    "commonData": {
      "status": "200",
      "authKey": "1111"
    },
    "aplData": {
      "name": "ZXS",
      "sex": "男",
      "birth": "19491001",
      "age": "26",
      "address": "上海市徐汇区",
      "phone": "1769862201",
      "email": "1769862201@qq.com",
      "wechat": "1769862201",
      "github": "https://github.com/chousann",
      "info": [
        {
          "index": "1",
          "type": "姓名",
          "descri": "ZXS"
        },
        {
          "index": "2",
          "type": "性别",
          "descri": "男"
        },
        {
          "index": "3",
          "type": "出生",
          "descri": "1949年10月"
        },
        {
          "index": "4",
          "type": "民族",
          "descri": "汉"
        },
        {
          "index": "5",
          "type": "工作描述",
          "descri": "上海海隆软件有限公司上海海隆软件有限公司上海海隆软件有限公司上海海隆软件有限公司上海海隆软件有限公司上海海隆软件有限公司"
        },
        {
          "index": "6",
          "type": "工作职责",
          "descri": "上海海隆软件有限公司上海海隆软件有限公司上海海隆软件有限公司上海海隆软件有限公司上海海隆软件有限公司上海海隆软件有限公司"
        },
        {
          "index": "7",
          "type": "完成业绩",
          "descri": "上海海隆软件有限公司上海海隆软件有限公司上海海隆软件有限公司上海海隆软件有限公司上海海隆软件有限公司上海海隆软件有限公司"
        }
      ],
      "education": [
        {
          "index": "1",
          "type": "学校名称",
          "descri": "上海海隆软件有限公司"
        },
        {
          "index": "2",
          "type": "就读时间",
          "descri": "2012年7月-2016年7月"
        },
        {
          "index": "3",
          "type": "所学专业",
          "descri": "电子信息科学与技术"
        },
        {
          "index": "4",
          "type": "学历学位",
          "descri": "本科 学士"
        },
        {
          "index": "5",
          "type": "工作描述",
          "descri": "上海海隆软件有限公司上海海隆软件有限公司上海海隆软件有限公司上海海隆软件有限公司上海海隆软件有限公司上海海隆软件有限公司"
        },
        {
          "index": "6",
          "type": "工作职责",
          "descri": "上海海隆软件有限公司上海海隆软件有限公司上海海隆软件有限公司上海海隆软件有限公司上海海隆软件有限公司上海海隆软件有限公司"
        },
        {
          "index": "7",
          "type": "完成业绩",
          "descri": "上海海隆软件有限公司上海海隆软件有限公司上海海隆软件有限公司上海海隆软件有限公司上海海隆软件有限公司上海海隆软件有限公司"
        }
      ],
      "job": [
        {
          "index": "1",
          "type": "公司名称",
          "descri": "上海海隆软件有限公司"
        },
        {
          "index": "2",
          "type": "工作时间",
          "descri": "2016年7月至今"
        },
        {
          "index": "3",
          "type": "所学专业",
          "descri": "pm"
        },
        {
          "index": "4",
          "type": "学历学位",
          "descri": "yyyy"
        },
        {
          "index": "5",
          "type": "工作描述",
          "descri": "上海海隆软件有限公司上海海隆软件有限公司上海海隆软件有限公司上海海隆软件有限公司上海海隆软件有限公司上海海隆软件有限公司"
        },
        {
          "index": "6",
          "type": "工作职责",
          "descri": "上海海隆软件有限公司上海海隆软件有限公司上海海隆软件有限公司上海海隆软件有限公司上海海隆软件有限公司上海海隆软件有限公司"
        },
        {
          "index": "7",
          "type": "完成业绩",
          "descri": "上海海隆软件有限公司上海海隆软件有限公司上海海隆软件有限公司上海海隆软件有限公司上海海隆软件有限公司上海海隆软件有限公司"
        }
      ],
      "project": [
        {
          "index": "1",
          "type": "学校名称",
          "descri": "上海海隆软件有限公司"
        },
        {
          "index": "2",
          "type": "就读时间",
          "descri": "2016年7月至今"
        },
        {
          "index": "3",
          "type": "所学专业",
          "descri": "pm"
        },
        {
          "index": "4",
          "type": "学历学位",
          "descri": "yyyy"
        },
        {
          "index": "5",
          "type": "工作描述",
          "descri": "上海海隆软件有限公司上海海隆软件有限公司上海海隆软件有限公司上海海隆软件有限公司上海海隆软件有限公司上海海隆软件有限公司"
        },
        {
          "index": "6",
          "type": "工作职责",
          "descri": "上海海隆软件有限公司上海海隆软件有限公司上海海隆软件有限公司上海海隆软件有限公司上海海隆软件有限公司上海海隆软件有限公司"
        },
        {
          "index": "7",
          "type": "完成业绩",
          "descri": "上海海隆软件有限公司上海海隆软件有限公司上海海隆软件有限公司上海海隆软件有限公司上海海隆软件有限公司上海海隆软件有限公司"
        }
      ],
      "skill": [
        {
          "index": "1",
          "type": "学校名称",
          "descri": "上海海隆软件有限公司"
        },
        {
          "index": "2",
          "type": "就读时间",
          "descri": "2016年7月至今"
        },
        {
          "index": "3",
          "type": "所学专业",
          "descri": "se"
        },
        {
          "index": "4",
          "type": "学历学位",
          "descri": "yyyy"
        },
        {
          "index": "5",
          "type": "工作描述",
          "descri": "上海海隆软件有限公司上海海隆软件有限公司上海海隆软件有限公司上海海隆软件有限公司上海海隆软件有限公司上海海隆软件有限公司"
        },
        {
          "index": "6",
          "type": "工作职责",
          "descri": "上海海隆软件有限公司上海海隆软件有限公司上海海隆软件有限公司上海海隆软件有限公司上海海隆软件有限公司上海海隆软件有限公司"
        },
        {
          "index": "7",
          "type": "完成业绩",
          "descri": "上海海隆软件有限公司上海海隆软件有限公司上海海隆软件有限公司上海海隆软件有限公司上海海隆软件有限公司上海海隆软件有限公司"
        }
      ],
      "intention": [
        {
          "index": "1",
          "type": "学校名称",
          "descri": "上海海隆软件有限公司"
        },
        {
          "index": "2",
          "type": "就读时间",
          "descri": "2016年7月至今"
        },
        {
          "index": "3",
          "type": "所学专业",
          "descri": "se"
        },
        {
          "index": "4",
          "type": "学历学位",
          "descri": "yyyy"
        },
        {
          "index": "5",
          "type": "工作描述",
          "descri": "上海海隆软件有限公司上海海隆软件有限公司上海海隆软件有限公司上海海隆软件有限公司上海海隆软件有限公司上海海隆软件有限公司"
        },
        {
          "index": "6",
          "type": "工作职责",
          "descri": "上海海隆软件有限公司上海海隆软件有限公司上海海隆软件有限公司上海海隆软件有限公司上海海隆软件有限公司上海海隆软件有限公司"
        },
        {
          "index": "7",
          "type": "完成业绩",
          "descri": "上海海隆软件有限公司上海海隆软件有限公司上海海隆软件有限公司上海海隆软件有限公司上海海隆软件有限公司上海海隆软件有限公司"
        }
      ],
      "selfevaluation": [
        {
          "index": "1",
          "type": "学校名称",
          "descri": "上海海隆软件有限公司"
        },
        {
          "index": "2",
          "type": "就读时间",
          "descri": "2016年7月至今"
        },
        {
          "index": "3",
          "type": "所学专业",
          "descri": "se"
        },
        {
          "index": "4",
          "type": "学历学位",
          "descri": "yyyy"
        },
        {
          "index": "5",
          "type": "工作描述",
          "descri": "上海海隆软件有限公司上海海隆软件有限公司上海海隆软件有限公司上海海隆软件有限公司上海海隆软件有限公司上海海隆软件有限公司"
        },
        {
          "index": "6",
          "type": "工作职责",
          "descri": "上海海隆软件有限公司上海海隆软件有限公司上海海隆软件有限公司上海海隆软件有限公司上海海隆软件有限公司上海海隆软件有限公司"
        },
        {
          "index": "7",
          "type": "完成业绩",
          "descri": "上海海隆软件有限公司上海海隆软件有限公司上海海隆软件有限公司上海海隆软件有限公司上海海隆软件有限公司上海海隆软件有限公司"
        }
      ]
    }
  },
  "check": {
    "commonData": {
      "status": "200"
    },
    "aplData": {}
  },
  "db": [],
  "api": []
}